ssmrun/__init__.py
ssmrun/cli.py
ssmrun/ssm.py
ssmrun-0.1.5.dist-info/DESCRIPTION.rst
ssmrun-0.1.5.dist-info/METADATA
ssmrun-0.1.5.dist-info/RECORD
ssmrun-0.1.5.dist-info/WHEEL
ssmrun-0.1.5.dist-info/entry_points.txt
ssmrun-0.1.5.dist-info/metadata.json
ssmrun-0.1.5.dist-info/top_level.txt
