Metadata-Version: 2.0
Name: ssmrun
Version: 0.1.5
Summary: Utilities for AWS EC2 SSM
Home-page: https://github.com/Fullscreen/ssmrun
Author: Fullscreen Devops
Author-email: devops@fullscreen.com
License: MIT license
Platform: UNKNOWN
Classifier: Development Status :: 2 - Pre-Alpha
Classifier: Programming Language :: Python
Classifier: Programming Language :: Python :: 2.6
Classifier: Programming Language :: Python :: 2.7
Classifier: Programming Language :: Python :: 3
Classifier: Programming Language :: Python :: 3.3
Classifier: Programming Language :: Python :: 3.4
Classifier: Programming Language :: Python :: 3.5
Classifier: Programming Language :: Python :: 3.6
Requires-Dist: Click (>=6.0)
Requires-Dist: boto3 (>=1.3.1)
